locopy/__init__.py
locopy/_version.py
locopy/database.py
locopy/errors.py
locopy/logger.py
locopy/redshift.py
locopy/s3.py
locopy/snowflake.py
locopy/utility.py
locopy-0.6.8.dist-info/licenses/LICENSE
locopy-0.6.8.dist-info/METADATA
locopy-0.6.8.dist-info/WHEEL
locopy-0.6.8.dist-info/top_level.txt
locopy-0.6.8.dist-info/RECORD
