Metadata-Version: 2.4
Name: locopy
Version: 0.6.8
Summary: Loading/Unloading to Amazon Redshift using Python
Author-email: Faisal Dosani <faisal.dosani@capitalone.com>
License: Apache Software License
Project-URL: Homepage, https://github.com/capitalone/locopy
Project-URL: Documentation, https://capitalone.github.io/locopy/
Classifier: Intended Audience :: Developers
Classifier: Natural Language :: English
Classifier: Operating System :: OS Independent
Classifier: Programming Language :: Python
Classifier: Programming Language :: Python :: 3
Classifier: Programming Language :: Python :: 3 :: Only
Classifier: Programming Language :: Python :: 3.9
Classifier: Programming Language :: Python :: 3.10
Classifier: Programming Language :: Python :: 3.11
Classifier: Programming Language :: Python :: 3.12
Requires-Python: >=3.9.0
License-File: LICENSE
Requires-Dist: boto3<=1.42.34,>=1.9.92
Requires-Dist: PyYAML<=6.0.2,>=5.1
Requires-Dist: pandas<=2.3.3,>=1.5.0
Requires-Dist: numpy<=2.2.6,>=1.22.0
Requires-Dist: polars>=0.20.0
Requires-Dist: pyarrow>=10.0.1
Provides-Extra: psycopg2
Requires-Dist: psycopg2-binary>=2.7.7; extra == "psycopg2"
Provides-Extra: pg8000
Requires-Dist: pg8000>=1.13.1; extra == "pg8000"
Provides-Extra: snowflake
Requires-Dist: snowflake-connector-python[pandas]>=2.1.2; extra == "snowflake"
Provides-Extra: docs
Requires-Dist: sphinx; extra == "docs"
Requires-Dist: sphinx_rtd_theme; extra == "docs"
Provides-Extra: tests
Requires-Dist: hypothesis; extra == "tests"
Requires-Dist: pytest; extra == "tests"
Requires-Dist: pytest-cov; extra == "tests"
Provides-Extra: qa
Requires-Dist: pre-commit; extra == "qa"
Requires-Dist: ruff==0.11.12; extra == "qa"
Provides-Extra: build
Requires-Dist: build; extra == "build"
Requires-Dist: twine; extra == "build"
Requires-Dist: wheel; extra == "build"
Provides-Extra: edgetest
Requires-Dist: edgetest; extra == "edgetest"
Requires-Dist: edgetest-conda; extra == "edgetest"
Provides-Extra: dev
Requires-Dist: locopy[tests]; extra == "dev"
Requires-Dist: locopy[docs]; extra == "dev"
Requires-Dist: locopy[qa]; extra == "dev"
Requires-Dist: locopy[build]; extra == "dev"
Dynamic: license-file
